konko/__init__.py
konko/chat_completion.py
konko/completion.py
konko/embedding.py
konko/model.py
konko/version.py
konko-0.5.0.dist-info/METADATA
konko-0.5.0.dist-info/WHEEL
konko-0.5.0.dist-info/RECORD
