Metadata-Version: 2.1
Name: konko
Version: 0.5.0
Summary: "Konko AI Python SDK: A client library to interact with Konko AI's API. With this SDK, developers can integrate, evaluate, fine-tune, and deploy Large Language Models (LLMs) using Konko AI's fully-managed, SOC 2 compliant platform. Ideal for enterprise use-cases, it allows you to focus on building great products without worrying about infrastructure."
License: Proprietary
Author: Konko AI
Author-email: support@konko.ai
Requires-Python: >=3.8
Classifier: License :: Other/Proprietary License
Classifier: Programming Language :: Python :: 3
Classifier: Programming Language :: Python :: 3.8
Classifier: Programming Language :: Python :: 3.9
Classifier: Programming Language :: Python :: 3.10
Classifier: Programming Language :: Python :: 3.11
Classifier: Programming Language :: Python :: 3.12
Requires-Dist: openai (<2)
